{
  "generator-jhipster": {
    "promptValues": {
      "packageName": "com.mycompany.myapp",
      "nativeLanguage": "en"
    },
    "jhipsterVersion": "4.14.0",
    "baseName": "mysql",
    "packageName": "com.mycompany.myapp",
    "packageFolder": "com/mycompany/myapp",
    "serverPort": "8080",
    "authenticationType": "jwt",
    "cacheProvider": "ehcache",
    "enableHibernateCache": true,
    "websocket": false,
    "databaseType": "sql",
    "devDatabaseType": "h2Disk",
    "prodDatabaseType": "mssql",
    "searchEngine": false,
    "messageBroker": false,
    "serviceDiscoveryType": false,
    "buildTool": "maven",
    "enableSocialSignIn": false,
    "enableSwaggerCodegen": false,
    "jwtSecretKey": "39f6259a5fbdc30588c530e5aadc37bb9ebf5b09",
    "clientFramework": "angularX",
    "useSass": false,
    "clientPackageManager": "yarn",
    "applicationType": "monolith",
    "testFrameworks": [],
    "jhiPrefix": "jhi",
    "enableTranslation": true,
    "nativeLanguage": "en",
    "languages": [
      "en"
    ],
    "reactive": false
  }
}